neon_tts_plugin_glados/__init__.py
neon_tts_plugin_glados/utils/__init__.py
neon_tts_plugin_glados/utils/numbers.py
neon_tts_plugin_glados/utils/symbols.py
neon_tts_plugin_glados-0.0.3a2.dist-info/METADATA
neon_tts_plugin_glados-0.0.3a2.dist-info/WHEEL
neon_tts_plugin_glados-0.0.3a2.dist-info/entry_points.txt
neon_tts_plugin_glados-0.0.3a2.dist-info/top_level.txt
neon_tts_plugin_glados-0.0.3a2.dist-info/zip-safe
neon_tts_plugin_glados-0.0.3a2.dist-info/RECORD
